flake8_bas/__init__.py
flake8_bas/checker.py
flake8_bas-1.0.0.dist-info/WHEEL
flake8_bas-1.0.0.dist-info/METADATA
flake8_bas-1.0.0.dist-info/entry_points.txt
flake8_bas-1.0.0.dist-info/LICENSE
flake8_bas-1.0.0.dist-info/RECORD
