Metadata-Version: 2.1
Name: flake8-bas
Version: 1.0.0
Summary: Flake8 extension that checks for blank lines around (compound) statements.
Home-page: https://github.com/ts-mk/flake8-bas/
License: MIT
Author: Tomas Mrozek
Author-email: tm@nohup.run
Maintainer: Tomas Mrozek
Maintainer-email: tm@nohup.run
Requires-Python: >=3.8.1,<4
Classifier: Environment :: Console
Classifier: Framework :: Flake8
Classifier: License :: OSI Approved :: MIT License
Classifier: Operating System :: OS Independent
Classifier: Programming Language :: Python
Classifier: Programming Language :: Python :: 3
Classifier: Programming Language :: Python :: 3.9
Classifier: Programming Language :: Python :: 3.10
Classifier: Programming Language :: Python :: 3.11
Classifier: Programming Language :: Python :: 3.10
Classifier: Programming Language :: Python :: 3.11
Classifier: Programming Language :: Python :: 3.12
Classifier: Programming Language :: Python :: 3.8
Classifier: Programming Language :: Python :: 3.9
Classifier: Topic :: Software Development :: Documentation
Classifier: Topic :: Software Development :: Libraries :: Python Modules
Classifier: Topic :: Software Development :: Quality Assurance
Requires-Dist: flake8 (>=3.8.0)
Requires-Dist: setuptools
Project-URL: Documentation, https://github.com/ts-mk/flake8-bas/blob/master/README.md
Project-URL: Repository, https://github.com/ts-mk/flake8-bas/
